django_autocomplete/__init__.py
django_autocomplete/core.py
django_autocomplete/utils.py
django_autocomplete/management/commands/generate_index.py
django_autocomplete_package-0.1.2.dist-info/METADATA
django_autocomplete_package-0.1.2.dist-info/WHEEL
django_autocomplete_package-0.1.2.dist-info/entry_points.txt
django_autocomplete_package-0.1.2.dist-info/top_level.txt
django_autocomplete_package-0.1.2.dist-info/RECORD
