Metadata-Version: 2.4
Name: django-autocomplete-package
Version: 0.1.2
Summary: A Django plugin for automatic class imports
Author-email: Neeraj Kumar <4094.neeraj@gmail.com>
License: MIT
Classifier: Development Status :: 3 - Alpha
Classifier: Intended Audience :: Developers
Classifier: License :: OSI Approved :: MIT License
Classifier: Operating System :: OS Independent
Classifier: Programming Language :: Python :: 3
Classifier: Programming Language :: Python :: 3.7
Classifier: Programming Language :: Python :: 3.8
Classifier: Programming Language :: Python :: 3.9
Classifier: Programming Language :: Python :: 3.10
Classifier: Framework :: Django
Classifier: Framework :: Django :: 3.2
Classifier: Framework :: Django :: 4.0
Requires-Python: >=3.7
Requires-Dist: Django>=3.2
Requires-Dist: jedi>=0.18.0
Requires-Dist: pyreadline3; platform_system == "Windows"
